EasyObj/BetterDict.py
EasyObj/BetterList.py
EasyObj/BetterString.py
EasyObj/Symbol.py
EasyObj/__init__.py
EasyObj-0.2.8.dist-info/LICENSE
EasyObj-0.2.8.dist-info/METADATA
EasyObj-0.2.8.dist-info/WHEEL
EasyObj-0.2.8.dist-info/top_level.txt
EasyObj-0.2.8.dist-info/RECORD
