Metadata-Version: 2.1
Name: EasyObj
Version: 0.2.8
Summary: EasyObj lets you manipulate objects as easily as in JavaScript.
Home-page: https://github.com/Howardzhangdqs/EasyObj
Author: HowardZhangdqs
Author-email: zjh@shanghaiit.com
License: GPL-3.0
Classifier: Programming Language :: Python :: 3
Requires-Python: >=3.8
License-File: LICENSE
